aiusage/__init__.py
aiusage/cli.py
aiusage/config.py
aiusage/core.py
aiusage/py.typed
aiusage-0.1.0.dist-info/WHEEL
aiusage-0.1.0.dist-info/entry_points.txt
aiusage-0.1.0.dist-info/METADATA
aiusage-0.1.0.dist-info/RECORD
