Metadata-Version: 2.3
Name: aiusage
Version: 0.1.0
Summary: A smart command-line tool for tracking AI credit consumption across billing cycles
Keywords: ai,credits,usage,tracking,cursor,copilot
Author: Michael Kennedy
Author-email: Michael Kennedy <mikeckennedy@gmail.com>
License: MIT
Classifier: Development Status :: 4 - Beta
Classifier: Intended Audience :: Developers
Classifier: License :: OSI Approved :: MIT License
Classifier: Programming Language :: Python :: 3
Classifier: Programming Language :: Python :: 3.13
Classifier: Programming Language :: Python :: 3.14
Classifier: Topic :: Utilities
Requires-Dist: platformdirs>=4.0.0
Requires-Dist: cyclopts>=3.0.0
Requires-Dist: pytest>=8.0.0 ; extra == 'dev'
Requires-Dist: pytest-cov>=6.0.0 ; extra == 'dev'
Requires-Dist: pytest-clarity>=1.0.0 ; extra == 'dev'
Requires-Dist: ruff>=0.14.0 ; extra == 'dev'
Requires-Dist: mypy>=1.0.0 ; extra == 'dev'
Requires-Dist: pyrefly>=0.1.0 ; extra == 'dev'
Requires-Python: >=3.13
Project-URL: Homepage, https://github.com/mikeckennedy/aiusage
Project-URL: Repository, https://github.com/mikeckennedy/aiusage
Provides-Extra: dev
